sbomgen/__init__.py
sbomgen/main.py
sbomgen/Parsers/conanParser.py
sbomgen/Parsers/dartParser.py
sbomgen/Parsers/dotnetParser.py
sbomgen/Parsers/gomodParser.py
sbomgen/Parsers/gradleGroovyParser.py
sbomgen/Parsers/gradlekotlinDSLParser.py
sbomgen/Parsers/mavenParser.py
sbomgen/Parsers/npmParser.py
sbomgen/Parsers/phpParser.py
sbomgen/Parsers/requirementsParser.py
sbomgen/Parsers/rubyParser.py
sbomgen/Parsers/rustParser.py
sbomgen/Parsers/swiftParser.py
sbomgen/Parsers/yarnParser.py
sbomgen/Utility/helpers.py
devcoderopop-1.0.0.dist-info/License.txt
devcoderopop-1.0.0.dist-info/METADATA
devcoderopop-1.0.0.dist-info/WHEEL
devcoderopop-1.0.0.dist-info/entry_points.txt
devcoderopop-1.0.0.dist-info/top_level.txt
devcoderopop-1.0.0.dist-info/RECORD
