Metadata-Version: 2.1
Name: devcoderopop
Version: 1.0.0
Summary: dcoder is op
Author: divyansh
Author-email: akashsah2003@gmail.com
License-File: License.txt
Requires-Dist: datetime
Requires-Dist: argparse
Requires-Dist: toml
